LICENSE
LICENSE.txt
MANIFEST.in
README.md
setup.cfg
setup.py
examples/core/2d_camera.py
examples/core/basic_screen_manager.py
examples/core/basic_window.py
examples/core/drop_files.py
examples/core/input_keys.py
examples/core/input_mouse.py
examples/core/input_mouse_wheel.py
examples/core/random_values.py
examples/core/split_screen.py
examples/core/resources/distortion100.fs
examples/core/resources/distortion330.fs
examples/core/resources/ps3.png
examples/core/resources/xbox.png
pyraylib/__init__.py
pyraylib/colors.py
pyraylib/easings.py
pyraylib.egg-info/PKG-INFO
pyraylib.egg-info/SOURCES.txt
pyraylib.egg-info/dependency_links.txt
pyraylib.egg-info/requires.txt
pyraylib.egg-info/top_level.txt
pyraylib/lib/libraylib.3.7.0.dylib
pyraylib/lib/libraylib.so
pyraylib/lib/raylib.dll