Metadata-Version: 2.1
Name: pyraylib
Version: 1.0.2
Summary: A Python binding for the great C library raylib
Home-page: https://github.com/Ho011/pyraylib
Author: Hussein Sarea
Author-email: zzzsssx0@gmail.com
License: MIT License
Project-URL: Bug Reports, https://github.com/Ho011/pyraylib/issues
Project-URL: Source, https://github.com/Ho011/pyraylib/
Keywords: raylib pyraylib easy-to-use OpenGL OGL 3D 2D game development
Platform: UNKNOWN
Classifier: Development Status :: 5 - Production/Stable
Classifier: Intended Audience :: Developers
Classifier: Topic :: Games/Entertainment
Classifier: License :: OSI Approved :: MIT License
Classifier: Programming Language :: Python :: 3 :: Only
Classifier: Programming Language :: Python :: 3.4
Classifier: Programming Language :: Python :: 3.5
Classifier: Programming Language :: Python :: 3.6
Classifier: Programming Language :: Python :: 3.7
Requires-Python: >=3.3, <4
License-File: LICENSE
License-File: LICENSE.txt
